CAM2ImageArchiver/CAM2ImageArchiver.py
CAM2ImageArchiver/CameraHandler.py
CAM2ImageArchiver/StreamParser.py
CAM2ImageArchiver/__init__.py
CAM2ImageArchiver/camera.py
CAM2ImageArchiver/error.py
CAM2ImageArchiver/utils.py
CAM2ImageArchiver-2.0.4.dist-info/LICENSE.txt
CAM2ImageArchiver-2.0.4.dist-info/METADATA
CAM2ImageArchiver-2.0.4.dist-info/WHEEL
CAM2ImageArchiver-2.0.4.dist-info/top_level.txt
CAM2ImageArchiver-2.0.4.dist-info/RECORD
