Metadata-Version: 2.1
Name: CAM2ImageArchiver
Version: 2.0.4
Summary: Network camera image retrieval and archiving.
Home-page: https://github.com/cam2proj/CAM2ImageArchiver
Author: Purdue CAM2 Research Group
Author-email: cam2proj@ecn.purdue.edu
License: Apache License 2.0
Download-URL: https://github.com/cam2proj/CAM2ImageArchiver/archive/1.0.tar.gz
Keywords: computer,vision,CAM2
Platform: UNKNOWN
Classifier: Development Status :: 5 - Production/Stable
Classifier: Programming Language :: Python :: 2.7
Classifier: Programming Language :: Python :: 3
Classifier: License :: OSI Approved :: Apache Software License
Requires-Python: >=2.7
Requires-Dist: certifi
Requires-Dist: chardet
Requires-Dist: funcsigs
Requires-Dist: idna
Requires-Dist: mock
Requires-Dist: numpy
Requires-Dist: pbr
Requires-Dist: pytz
Requires-Dist: requests
Requires-Dist: opencv-python
